sinapsis_data_analysis/__init__.py
sinapsis_data_analysis/helpers/__init__.py
sinapsis_data_analysis/helpers/excluded_models.py
sinapsis_data_analysis/helpers/model_metrics.py
sinapsis_data_analysis/helpers/tags.py
sinapsis_data_analysis/templates/__init__.py
sinapsis_data_analysis/templates/ml_base_inference.py
sinapsis_data_analysis/templates/ml_base_training.py
sinapsis_data_analysis/templates/sklearn_inference.py
sinapsis_data_analysis/templates/sklearn_manifold.py
sinapsis_data_analysis/templates/sklearn_train.py
sinapsis_data_analysis/templates/xgboost_inference.py
sinapsis_data_analysis/templates/xgboost_train.py
sinapsis_data_analysis-0.1.10.dist-info/licenses/LICENSE
sinapsis_data_analysis-0.1.10.dist-info/METADATA
sinapsis_data_analysis-0.1.10.dist-info/WHEEL
sinapsis_data_analysis-0.1.10.dist-info/top_level.txt
sinapsis_data_analysis-0.1.10.dist-info/RECORD
