Metadata-Version: 2.4
Name: sinapsis-data-analysis
Version: 0.1.10
Summary: Templates to work with models for classification, regression and clustering with xgboost and sklearn.
Author-email: SinapsisAI <dev@sinapsis.tech>
Project-URL: Homepage, https://sinapsis.tech
Project-URL: Documentation, https://docs.sinapsis.tech/docs
Project-URL: Tutorials, https://docs.sinapsis.tech/tutorials
Project-URL: Repository, https://github.com/Sinapsis-AI/sinapsis-data-tools.git
Requires-Python: >=3.10
License-File: LICENSE
Requires-Dist: scikit-learn>=1.6.1
Requires-Dist: sinapsis>=0.1.1
Requires-Dist: sinapsis-data-readers
Requires-Dist: xgboost>=3.0.0
Dynamic: license-file
